turkyazim/__init__.py
turkyazim/bert_denetleyici.py
turkyazim/cli.py
turkyazim/turkyazim.py
turkyazim/yazim_denetleyici.py
turkyazim-1.2.0.dist-info/licenses/LICENSE
turkyazim-1.2.0.dist-info/METADATA
turkyazim-1.2.0.dist-info/WHEEL
turkyazim-1.2.0.dist-info/entry_points.txt
turkyazim-1.2.0.dist-info/top_level.txt
turkyazim-1.2.0.dist-info/RECORD
