Metadata-Version: 2.4
Name: turkyazim
Version: 1.2.0
Summary: Gelişmiş Türkçe Yazım Denetleyici - Zemberek + BERT + TDK
Home-page: https://github.com/kullaniciadi/turkce-yazim-kontrol
Author: Umut573
Classifier: Programming Language :: Python :: 3
Classifier: License :: OSI Approved :: MIT License
Classifier: Operating System :: OS Independent
License-File: LICENSE
Requires-Dist: zemberek-python
Requires-Dist: python-Levenshtein
Requires-Dist: transformers
Requires-Dist: torch
Requires-Dist: fastapi
Requires-Dist: uvicorn
Requires-Dist: requests
Dynamic: author
Dynamic: classifier
Dynamic: description
Dynamic: description-content-type
Dynamic: home-page
Dynamic: license-file
Dynamic: requires-dist
Dynamic: summary
